azure_finops_mcp_server/__init__.py
azure_finops_mcp_server/config.py
azure_finops_mcp_server/main.py
azure_finops_mcp_server/main_refactored.py
azure_finops_mcp_server/monitoring.py
azure_finops_mcp_server/helpers/azure_client_factory.py
azure_finops_mcp_server/helpers/azure_utils.py
azure_finops_mcp_server/helpers/budget_operations.py
azure_finops_mcp_server/helpers/budget_operations_refactored.py
azure_finops_mcp_server/helpers/cache_manager.py
azure_finops_mcp_server/helpers/concurrent_util.py
azure_finops_mcp_server/helpers/cost_filters.py
azure_finops_mcp_server/helpers/disk_operations.py
azure_finops_mcp_server/helpers/error_handling.py
azure_finops_mcp_server/helpers/logging_config.py
azure_finops_mcp_server/helpers/network_operations.py
azure_finops_mcp_server/helpers/optimized_cost.py
azure_finops_mcp_server/helpers/parallel_processor.py
azure_finops_mcp_server/helpers/retry_handler.py
azure_finops_mcp_server/helpers/subscription_manager.py
azure_finops_mcp_server/helpers/util.py
azure_finops_mcp_server/helpers/validators.py
azure_finops_mcp_server/helpers/vm_operations.py
azure_finops_mcp_server-2.0.0.dist-info/licenses/LICENSE
azure_finops_mcp_server-2.0.0.dist-info/METADATA
azure_finops_mcp_server-2.0.0.dist-info/WHEEL
azure_finops_mcp_server-2.0.0.dist-info/entry_points.txt
azure_finops_mcp_server-2.0.0.dist-info/top_level.txt
azure_finops_mcp_server-2.0.0.dist-info/RECORD
