Metadata-Version: 2.4
Name: azure-finops-mcp-server
Version: 2.0.0
Summary: An MCP server for Azure FinOps to analyze costs and audit for savings.
Home-page: https://github.com/julianobarbosa/azure-finops-mcp-server
Author: Ravi Kiran Vallamkonda
Author-email: juliano.barbosa@example.com
License-Expression: MIT
Project-URL: Homepage, https://github.com/julianobarbosa/azure-finops-mcp-server
Project-URL: Source, https://github.com/julianobarbosa/azure-finops-mcp-server
Keywords: azure,cost,finops,cloud
Requires-Python: >=3.10
License-File: LICENSE
Requires-Dist: azure-identity
Requires-Dist: azure-mgmt-costmanagement
Requires-Dist: azure-mgmt-compute
Requires-Dist: azure-mgmt-network
Requires-Dist: azure-mgmt-consumption
Requires-Dist: azure-mgmt-resource
Requires-Dist: mcp[cli]
Dynamic: author-email
Dynamic: home-page
Dynamic: license-file
Dynamic: requires-python
